bottango_playback_interface/__init__.py
bottango_playback_interface/__main__.py
bottango_playback_interface-0.5.0rc0.dist-info/LICENSE
bottango_playback_interface-0.5.0rc0.dist-info/METADATA
bottango_playback_interface-0.5.0rc0.dist-info/WHEEL
bottango_playback_interface-0.5.0rc0.dist-info/entry_points.txt
bottango_playback_interface-0.5.0rc0.dist-info/RECORD
