Metadata-Version: 2.1
Name: bottango_playback_interface
Version: 0.5.0rc0
Summary: Bottango Playback Interface
License: Apache 2.0
Author: Martin Rioux
Requires-Python: >=3.7.0,<4.0.0
Classifier: License :: Other/Proprietary License
Classifier: Programming Language :: Python :: 3
Classifier: Programming Language :: Python :: 3.7
Classifier: Programming Language :: Python :: 3.8
Classifier: Programming Language :: Python :: 3.9
Classifier: Programming Language :: Python :: 3.10
Classifier: Programming Language :: Python :: 3.11
